pyharbor/__init__.py
pyharbor/harbor_client.py
pyharborsdk-0.1.dist-info/LICENSE
pyharborsdk-0.1.dist-info/METADATA
pyharborsdk-0.1.dist-info/WHEEL
pyharborsdk-0.1.dist-info/top_level.txt
pyharborsdk-0.1.dist-info/RECORD
