Metadata-Version: 2.1
Name: pyharborsdk
Version: 0.1
Summary: SDK about harbor
Home-page: https://github.com/ThinkBlue1991/pyharbortool
Author: zhangjx
Author-email: 1075495029@qq.com
License: UNKNOWN
Platform: UNKNOWN
Classifier: Programming Language :: Python :: 3
Classifier: License :: OSI Approved :: MIT License
Classifier: Operating System :: OS Independent
